CHANGES.txt
LICENSE.txt
MANIFEST.in
README.rst
distribute_setup.py
requirements.txt
setup.py
TornadIO2Go.egg-info/PKG-INFO
TornadIO2Go.egg-info/SOURCES.txt
TornadIO2Go.egg-info/dependency_links.txt
TornadIO2Go.egg-info/requires.txt
TornadIO2Go.egg-info/top_level.txt
examples/manage.py
examples/doodle/__init__.py
examples/doodle/models.py
examples/doodle/socketioconnection.py
examples/doodle/tests.py
examples/doodle/views.py
examples/doodle/static/js/jquery-1.9.0.min.js
examples/doodle/static/js/main.js
examples/doodle/static/js/socket.io.js
examples/doodle/static/js/underscore-min.js
examples/doodle/templates/doodle/index.html
examples/tornadio2go_sample/__init__.py
examples/tornadio2go_sample/settings.py
examples/tornadio2go_sample/urls.py
examples/tornadio2go_sample/wsgi.py
tornadio2go/__init__.py
tornadio2go/models.py
tornadio2go/signals.py
tornadio2go/tests.py
tornadio2go/views.py
tornadio2go/management/__init__.py
tornadio2go/management/commands/__init__.py
tornadio2go/management/commands/runtornadio2.py