Metadata-Version: 1.0
Name: TornadIO2Go
Version: 1.0.4
Summary: Seamlessly run your Django and TornadIO2 project inside Tornado. Like.A.Boss.
Home-page: https://github.com/rudeb0t/tornadio2go
Author: Nimrod A. Abing
Author-email: nimrod.abing@gmail.com
License: LICENSE.txt
Platform: UNKNOWN
